nivo_chart/__init__.py
nivo_chart/frontend/build/asset-manifest.json
nivo_chart/frontend/build/index.html
nivo_chart/frontend/build/precache-manifest.0b1f7f36030c899b7025350315e7101c.js
nivo_chart/frontend/build/service-worker.js
nivo_chart/frontend/build/static/js/2.52f8f681.chunk.js
nivo_chart/frontend/build/static/js/2.52f8f681.chunk.js.LICENSE.txt
nivo_chart/frontend/build/static/js/2.52f8f681.chunk.js.map
nivo_chart/frontend/build/static/js/main.27f25157.chunk.js
nivo_chart/frontend/build/static/js/main.27f25157.chunk.js.map
nivo_chart/frontend/build/static/js/runtime-main.7e2c8680.js
nivo_chart/frontend/build/static/js/runtime-main.7e2c8680.js.map
streamlit_nivo-0.1.8.dist-info/LICENSE
streamlit_nivo-0.1.8.dist-info/METADATA
streamlit_nivo-0.1.8.dist-info/WHEEL
streamlit_nivo-0.1.8.dist-info/top_level.txt
streamlit_nivo-0.1.8.dist-info/RECORD
