Metadata-Version: 2.1
Name: streamlit-nivo
Version: 0.1.8
Summary: Render Nivo charts in Streamlit
Home-page: https://github.com/aswan-heart-centre/streamlit_nivo
Author: Ahmed Saleh
Author-email: a.saleh.ismael@gmail.com
License: UNKNOWN
Platform: UNKNOWN
Requires-Python: >=3.6
License-File: LICENSE
Requires-Dist: streamlit (>=0.63)
